dbt_cloud_run_runner/__init__.py
dbt_cloud_run_runner/client.py
dbt_cloud_run_runner/models.py
tests/__init__.py
tests/test_e2e.py
dbt_cloud_run_runner-0.2.0.dist-info/METADATA
dbt_cloud_run_runner-0.2.0.dist-info/WHEEL
dbt_cloud_run_runner-0.2.0.dist-info/top_level.txt
dbt_cloud_run_runner-0.2.0.dist-info/RECORD
