Metadata-Version: 2.4
Name: dbt-cloud-run-runner
Version: 0.2.0
Summary: A client library for running dbt projects on Google Cloud Run
License: Proprietary
Project-URL: Homepage, https://github.com/delphiio/dbt-runners
Project-URL: Bug Tracker, https://github.com/delphiio/dbt-runners/issues
Keywords: dbt,cloud-run,gcp,bigquery,data-engineering
Classifier: Development Status :: 4 - Beta
Classifier: Intended Audience :: Developers
Classifier: Operating System :: OS Independent
Classifier: Programming Language :: Python :: 3
Classifier: Programming Language :: Python :: 3.9
Classifier: Programming Language :: Python :: 3.10
Classifier: Programming Language :: Python :: 3.11
Classifier: Programming Language :: Python :: 3.12
Requires-Python: >=3.9
Requires-Dist: google-cloud-storage>=2.0.0
Requires-Dist: google-cloud-run>=0.10.0
Requires-Dist: pyyaml>=6.0
Provides-Extra: dev
Requires-Dist: pytest>=7.0.0; extra == "dev"
Requires-Dist: pytest-cov>=4.0.0; extra == "dev"
Requires-Dist: black>=23.0.0; extra == "dev"
Requires-Dist: mypy>=1.0.0; extra == "dev"
